darktrace/__init__.py
darktrace/auth.py
darktrace/client.py
darktrace/dt_advanced_search.py
darktrace/dt_analyst.py
darktrace/dt_antigena.py
darktrace/dt_breaches.py
darktrace/dt_components.py
darktrace/dt_cves.py
darktrace/dt_details.py
darktrace/dt_deviceinfo.py
darktrace/dt_devices.py
darktrace/dt_devicesearch.py
darktrace/dt_devicesummary.py
darktrace/dt_email.py
darktrace/dt_endpointdetails.py
darktrace/dt_enums.py
darktrace/dt_filtertypes.py
darktrace/dt_intelfeed.py
darktrace/dt_mbcomments.py
darktrace/dt_metricdata.py
darktrace/dt_metrics.py
darktrace/dt_models.py
darktrace/dt_network.py
darktrace/dt_pcaps.py
darktrace/dt_similardevices.py
darktrace/dt_status.py
darktrace/dt_subnets.py
darktrace/dt_summarystatistics.py
darktrace/dt_tags.py
darktrace/dt_utils.py
darktrace_sdk-1.0.5.dist-info/licenses/LICENSE
darktrace_sdk-1.0.5.dist-info/METADATA
darktrace_sdk-1.0.5.dist-info/WHEEL
darktrace_sdk-1.0.5.dist-info/top_level.txt
darktrace_sdk-1.0.5.dist-info/RECORD
