Metadata-Version: 2.4
Name: darktrace-sdk
Version: 1.0.5
Summary: A modern, modular, and complete Python SDK for the Darktrace API
Home-page: https://github.com/LegendEvent/darktrace-sdk
Author: LegendEvent
Author-email: ridge.thrill7680@eagereverest.com
License: MIT
Keywords: darktrace sdk api security threat-visualizer
Classifier: Programming Language :: Python :: 3
Classifier: License :: OSI Approved :: MIT License
Classifier: Operating System :: OS Independent
Classifier: Intended Audience :: Developers
Classifier: Intended Audience :: Information Technology
Classifier: Topic :: Security
Classifier: Topic :: Software Development :: Libraries :: Python Modules
Requires-Python: >=3.7
License-File: LICENSE
Requires-Dist: requests>=2.25.1
Dynamic: author
Dynamic: author-email
Dynamic: classifier
Dynamic: description
Dynamic: description-content-type
Dynamic: home-page
Dynamic: keywords
Dynamic: license
Dynamic: license-file
Dynamic: requires-dist
Dynamic: requires-python
Dynamic: summary
